gpuctl/__init__.py
gpuctl/eth_ctl.py
gpuctl/eth_main.py
gpuctl/gpu_amd.py
gpuctl/gpu_ctl.py
gpuctl/gpu_dev.py
gpuctl/gpu_main.py
gpuctl/gpu_mock.py
gpuctl/gpu_nv.py
gpuctl/main.py
gpuctl/miner_ctl.py
gpuctl/utils.py
gpuctl/version.py
gpuctl-0.3.6.dist-info/LICENSE
gpuctl-0.3.6.dist-info/METADATA
gpuctl-0.3.6.dist-info/WHEEL
gpuctl-0.3.6.dist-info/entry_points.txt
gpuctl-0.3.6.dist-info/top_level.txt
gpuctl-0.3.6.dist-info/RECORD
