Metadata-Version: 2.1
Name: gpuctl
Version: 0.3.6
Summary: GPU contorl and failure notification/recovery
Home-page: https://github.com/Ed-Yang/gpuctl
Author: Edward Yang
Author-email: edwardyangyang@hotmail.com
License: MIT
Download-URL: https://github.com/Ed-Yang/gpuctl/archive/refs/tags/0.3.6.tar.gz
Keywords: gpu amd nvidia ai pytorch tensorflow torch mining ethereum bitcoin cryptocurrency ethminer nsfminer phoenixminer
Platform: UNKNOWN
Requires-Python: >=3
Requires-Dist: setuptools
Requires-Dist: wheel
Requires-Dist: pynvml
